pyelle/__init__.py
pyelle/elle.py
pyelle/exceptions.py
pyelle-0.1.0.dist-info/METADATA
pyelle-0.1.0.dist-info/WHEEL
pyelle-0.1.0.dist-info/top_level.txt
pyelle-0.1.0.dist-info/RECORD
