Metadata-Version: 2.4
Name: pyelle
Version: 0.1.0
Summary: An extensible, legible, line-based, elegant data solution!
Author: Preston Coley
Author-email: prestoncoley0920@proton.me
Classifier: Programming Language :: Python :: 3
Classifier: Operating System :: OS Independent
Requires-Python: >=3.6
Dynamic: author
Dynamic: author-email
Dynamic: classifier
Dynamic: description
Dynamic: description-content-type
Dynamic: requires-python
Dynamic: summary
